mtg_print/__init__.py
mtg_print/__version__.py
mtg_print/archidekt.py
mtg_print/basics.py
mtg_print/cache.py
mtg_print/cli.py
mtg_print/decklist.py
mtg_print/models.py
mtg_print/preferences.py
mtg_print/scryfall.py
mtg_print/sheet.py
mtg_print/terminal.py
mtg_print-0.5.0.dist-info/METADATA
mtg_print-0.5.0.dist-info/WHEEL
mtg_print-0.5.0.dist-info/entry_points.txt
mtg_print-0.5.0.dist-info/licenses/LICENSE
mtg_print-0.5.0.dist-info/RECORD
