Metadata-Version: 2.4
Name: mtg-print
Version: 0.5.0
Summary: CLI tool for printing MTG proxy sheets from decklists
Project-URL: Repository, https://github.com/jamiemc1/mtg-print
Project-URL: Issues, https://github.com/jamiemc1/mtg-print/issues
Author: Jamie McMillan
License-Expression: MIT
License-File: LICENSE
Keywords: decklist,magic,mtg,printing,proxy,scryfall
Classifier: Development Status :: 4 - Beta
Classifier: Environment :: Console
Classifier: Intended Audience :: End Users/Desktop
Classifier: License :: OSI Approved :: MIT License
Classifier: Operating System :: OS Independent
Classifier: Programming Language :: Python :: 3.11
Classifier: Programming Language :: Python :: 3.12
Classifier: Topic :: Games/Entertainment
Requires-Python: >=3.11
Requires-Dist: httpx>=0.27
Requires-Dist: pillow>=10.0
Requires-Dist: reportlab>=4.0
Requires-Dist: tomli-w>=1.0
Requires-Dist: typer>=0.9
